mpu_servocontrol/__init__.py
mpu_servocontrol/mainclass.py
mpu_servocontrol-0.1.2.dist-info/METADATA
mpu_servocontrol-0.1.2.dist-info/WHEEL
mpu_servocontrol-0.1.2.dist-info/top_level.txt
mpu_servocontrol-0.1.2.dist-info/RECORD
