Metadata-Version: 2.1
Name: mpu-servocontrol
Version: 0.1.2
Summary: beta version
Home-page: UNKNOWN
Author: Radu Alexandru
Author-email: radual3xandru6@gmail.com
License: MIT
Platform: UNKNOWN
Requires-Dist: smbus
